{"total":669,"pageSize":10,"pageCount":67,"data":[{"title":"12.Nginx日常实践整理记录","slug":"系统运维/Application/Web/WebApp/Nginx/12.Nginx日常实践整理记录","date":"2020-09-02T05:10:30.000Z","updated":"2022-10-10T09:36:51.567Z","url":"2020/9-2-591.html","path":"api/articles/2020/9-2-591.html.json","cover":"https://img.weiyigeek.top/2022/10/20221010141527.png","content":null,"comments":null,"excerpt":null,"keywords":null,"categories":[{"name":"实践整理","path":"api/categories/实践整理.json"}],"tags":[{"name":"Nginx","path":"api/tags/Nginx.json"}]},{"title":"1.Openresty高性能Web服务器基础介绍与部署配置实践指南","slug":"系统运维/Application/Web/WebApp/Openresty/Openresty收集中","date":"2020-09-01T05:34:30.000Z","updated":"2022-08-12T06:56:06.135Z","url":"2020/9-1-681.html","path":"api/articles/2020/9-1-681.html.json","cover":null,"content":null,"comments":null,"excerpt":null,"keywords":null,"categories":[{"name":"基础入门","path":"api/categories/基础入门.json"},{"name":"运维实践","path":"api/categories/运维实践.json"}],"tags":[{"name":"Nginx","path":"api/tags/Nginx.json"},{"name":"Web服务","path":"api/tags/Web服务.json"}]},{"title":"SQLite快速入门","slug":"数据存储/SQLite/SQLite快速入门","date":"2020-08-17T11:34:30.000Z","updated":"2020-10-10T02:37:43.162Z","url":"2020/8-17-54.html","path":"api/articles/2020/8-17-54.html.json","cover":null,"content":null,"comments":null,"excerpt":null,"keywords":null,"categories":[{"name":"数据库","path":"api/categories/数据库.json"}],"tags":[{"name":"SQLite","path":"api/tags/SQLite.json"}]},{"title":"1.Elastic Stack分布式数据采集搜索引擎基础入门介绍","slug":"网安防御/安全建设/日志审计/ElasticStack/1.ElasticStack分布式数据采集搜索引擎基础入门介绍","date":"2020-08-01T01:34:30.000Z","updated":"2022-06-15T02:46:31.946Z","url":"2020/8-1-568.html","path":"api/articles/2020/8-1-568.html.json","cover":"https://cdn.jsdelivr.net/gh/WeiyiGeek/blogimage/2021/5/20211006111827.png","content":null,"comments":null,"excerpt":null,"keywords":null,"categories":[{"name":"日志审计","path":"api/categories/日志审计.json"},{"name":"安全建设","path":"api/categories/安全建设.json"}],"tags":[{"name":"Elastic","path":"api/tags/Elastic.json"}]},{"title":"GitLab有趣的API接口实践","slug":"系统运维/自动化运维/CI-CD/Gitlab/GitLab有趣的API接口实践","date":"2020-07-22T12:35:30.000Z","updated":"2022-05-23T07:46:08.953Z","url":"2020/7-22-626.html","path":"api/articles/2020/7-22-626.html.json","cover":null,"content":null,"comments":null,"excerpt":null,"keywords":null,"categories":[{"name":"Git","path":"api/categories/Git.json"},{"name":"代码仓库","path":"api/categories/代码仓库.json"}],"tags":[{"name":"gitlab","path":"api/tags/gitlab.json"}]},{"title":"CIFS与CIFS Homedir文件系统学习总结","slug":"系统运维/Application/DiskManagement/NetworkStorage/CIFS与CIFS-Homedir网络文件系统学习总结","date":"2020-07-22T11:35:30.000Z","updated":"2022-07-10T02:05:16.955Z","url":"2020/7-22-102.html","path":"api/articles/2020/7-22-102.html.json","cover":"https://cdn.jsdelivr.net/gh/WeiyiGeek/blogimage/2020/1/20200811200752.png","content":null,"comments":null,"excerpt":null,"keywords":null,"categories":[{"name":"磁盘管理","path":"api/categories/磁盘管理.json"}],"tags":[{"name":"CIFS","path":"api/tags/CIFS.json"}]},{"title":"Flask基础学习之入坑出坑体验记录","slug":"编程世界/Python/Web开发/Flask/Flask基础学习之入坑出坑体验记录","date":"2020-07-16T12:34:30.000Z","updated":"2022-08-10T08:39:22.412Z","url":"2020/7-16-648.html","path":"api/articles/2020/7-16-648.html.json","cover":null,"content":null,"comments":null,"excerpt":null,"keywords":null,"categories":[{"name":"Python3","path":"api/categories/Python3.json"},{"name":"Web开发","path":"api/categories/Web开发.json"}],"tags":[{"name":"Flask","path":"api/tags/Flask.json"}]},{"title":"Flask基础入门学习笔记2","slug":"编程世界/Python/Web开发/Flask/基础入门/Flask基础入门学习笔记2","date":"2020-07-16T12:34:30.000Z","updated":"2022-04-10T00:46:12.418Z","url":"2020/7-16-331.html","path":"api/articles/2020/7-16-331.html.json","cover":"https://cdn.jsdelivr.net/gh/WeiyiGeek/blogimage/2020/1/20201011173716.png","content":null,"comments":null,"excerpt":null,"keywords":null,"categories":[{"name":"Python3","path":"api/categories/Python3.json"},{"name":"Web开发","path":"api/categories/Web开发.json"}],"tags":[{"name":"Flask","path":"api/tags/Flask.json"}]},{"title":"Flask基础入门学习笔记-1","slug":"编程世界/Python/Web开发/Flask/基础入门/Flask基础入门学习笔记1","date":"2020-07-16T12:34:30.000Z","updated":"2022-05-26T00:45:10.560Z","url":"2020/7-16-330.html","path":"api/articles/2020/7-16-330.html.json","cover":"https://cdn.jsdelivr.net/gh/WeiyiGeek/blogimage/2020/1/20200815210354.png","content":null,"comments":null,"excerpt":null,"keywords":null,"categories":[{"name":"Python3","path":"api/categories/Python3.json"},{"name":"Web开发","path":"api/categories/Web开发.json"}],"tags":[{"name":"Flask","path":"api/tags/Flask.json"}]},{"title":"Flask扩展使用笔记","slug":"编程世界/Python/Web开发/Flask/扩展进阶/Flask扩展使用笔记","date":"2020-07-16T12:34:30.000Z","updated":"2022-08-10T00:22:12.233Z","url":"2020/7-16-332.html","path":"api/articles/2020/7-16-332.html.json","cover":"https://cdn.jsdelivr.net/gh/WeiyiGeek/blogimage/2020/1/20200916230105.png","content":null,"comments":null,"excerpt":null,"keywords":null,"categories":[{"name":"Python3","path":"api/categories/Python3.json"},{"name":"Web开发","path":"api/categories/Web开发.json"}],"tags":[{"name":"Flask","path":"api/tags/Flask.json"},{"name":"Flask-扩展模块","path":"api/tags/Flask-扩展模块.json"}]}]}