{"total":670,"pageSize":10,"pageCount":67,"data":[{"title":"PS常用命令之系统WMI查看和操作相关命令","slug":"编程世界/Powershell/Cmdlet/系统信息类命令/PS常用命令之系统WMI查看和操作相关命令","date":"2019-12-19T07:36:30.000Z","updated":"2021-07-02T01:49:01.465Z","url":"2019/12-19-319.html","path":"api/articles/2019/12-19-319.html.json","cover":null,"content":null,"comments":null,"excerpt":null,"keywords":null,"categories":[{"name":"Development","path":"api/categories/Development.json"}],"tags":[{"name":"Powershell","path":"api/tags/Powershell.json"}]},{"title":"MySQL常用SQL收集","slug":"数据存储/MySQL/常用SQL收集","date":"2019-12-10T11:35:30.000Z","updated":"2022-10-18T09:27:09.077Z","url":"2019/12-10-630.html","path":"api/articles/2019/12-10-630.html.json","cover":null,"content":null,"comments":null,"excerpt":null,"keywords":null,"categories":[{"name":"Database","path":"api/categories/Database.json"},{"name":"关系型数据库","path":"api/categories/关系型数据库.json"}],"tags":[{"name":"MySQL","path":"api/tags/MySQL.json"}]},{"title":"BootStrap应用开发学习入门1","slug":"编程世界/前端技术/BootStrap/BootStrap应用开发学习入门1","date":"2019-12-09T10:34:30.000Z","updated":"2022-03-30T05:04:31.984Z","url":"2019/12-9-355.html","path":"api/articles/2019/12-9-355.html.json","cover":"https://cdn.jsdelivr.net/gh/WeiyiGeek/blogimage/2019/1/20191209171055.png","content":null,"comments":null,"excerpt":null,"keywords":null,"categories":[{"name":"jQuery","path":"api/categories/jQuery.json"},{"name":"前端技术","path":"api/categories/前端技术.json"}],"tags":[{"name":"BootStrap","path":"api/tags/BootStrap.json"}]},{"title":"MsSQL编程入门-待补充","slug":"数据存储/MSSQL/MsSQL编程入门","date":"2019-12-01T13:34:33.000Z","updated":"2022-04-13T14:44:35.779Z","url":"2019/12-1-42.html","path":"api/articles/2019/12-1-42.html.json","cover":"https://cdn.jsdelivr.net/gh/WeiyiGeek/blogimage/2020/1/20200429173603.png","content":null,"comments":null,"excerpt":null,"keywords":null,"categories":[{"name":"Database","path":"api/categories/Database.json"}],"tags":[{"name":"MsSQL","path":"api/tags/MsSQL.json"}]},{"title":"MySQL数据库编程基础入门1","slug":"数据存储/MySQL/MySQL数据库编程基础入门1","date":"2019-12-01T13:34:33.000Z","updated":"2022-03-29T05:39:06.312Z","url":"2019/12-1-43.html","path":"api/articles/2019/12-1-43.html.json","cover":"https://cdn.jsdelivr.net/gh/WeiyiGeek/blogimage/2020/1/20200115221136.png","content":null,"comments":null,"excerpt":null,"keywords":null,"categories":[{"name":"Database","path":"api/categories/Database.json"}],"tags":[{"name":"MySQL","path":"api/tags/MySQL.json"}]},{"title":"BootStrap插件组件使用总结","slug":"编程世界/前端技术/BootStrap/BootStrap插件组件使用总结","date":"2019-11-30T11:35:30.000Z","updated":"2022-03-30T04:53:59.959Z","url":"2019/11-30-356.html","path":"api/articles/2019/11-30-356.html.json","cover":"https://cdn.jsdelivr.net/gh/WeiyiGeek/blogimage/2020/1/20200729224904.png","content":null,"comments":null,"excerpt":null,"keywords":null,"categories":[{"name":"jQuery","path":"api/categories/jQuery.json"},{"name":"前端技术","path":"api/categories/前端技术.json"}],"tags":[{"name":"BootStrap","path":"api/tags/BootStrap.json"}]},{"title":"BootStrap应用开发学习入门","slug":"编程世界/前端技术/BootStrap/BootStrap应用开发学习入门0","date":"2019-11-29T10:34:30.000Z","updated":"2022-03-30T05:04:40.977Z","url":"2019/11-29-354.html","path":"api/articles/2019/11-29-354.html.json","cover":"https://cdn.jsdelivr.net/gh/WeiyiGeek/blogimage/2019/1/20191202162320.png","content":null,"comments":null,"excerpt":null,"keywords":null,"categories":[{"name":"jQuery","path":"api/categories/jQuery.json"},{"name":"前端技术","path":"api/categories/前端技术.json"}],"tags":[{"name":"BootStrap","path":"api/tags/BootStrap.json"}]},{"title":"Mac苹果系统安装之EXSI操作","slug":"系统运维/Mac/Mac苹果系统安装之EXSI安装操作","date":"2019-11-28T04:34:30.000Z","updated":"2022-03-29T05:39:06.304Z","url":"2019/11-28-217.html","path":"api/articles/2019/11-28-217.html.json","cover":"https://cdn.jsdelivr.net/gh/WeiyiGeek/blogimage/2019/1/20191113110420.png","content":null,"comments":null,"excerpt":null,"keywords":null,"categories":[{"name":"Systeminstall","path":"api/categories/Systeminstall.json"}],"tags":[{"name":"MacOS","path":"api/tags/MacOS.json"}]},{"title":"Mac苹果系统使用问题","slug":"系统运维/Mac/Mac苹果系统使用问题","date":"2019-11-28T04:34:30.000Z","updated":"2020-10-10T02:37:46.257Z","url":"2019/11-28-216.html","path":"api/articles/2019/11-28-216.html.json","cover":null,"content":null,"comments":null,"excerpt":null,"keywords":null,"categories":[{"name":"Systeminstall","path":"api/categories/Systeminstall.json"}],"tags":[{"name":"MacOS","path":"api/tags/MacOS.json"}]},{"title":"DELL服务器基础运维操作与错误处理","slug":"系统运维/Server/DELL/DELL服务器基础运维操作与错误处理","date":"2019-11-26T01:34:30.000Z","updated":"2022-03-29T05:39:06.305Z","url":"2019/11-26-220.html","path":"api/articles/2019/11-26-220.html.json","cover":"https://cdn.jsdelivr.net/gh/WeiyiGeek/blogimage/2019/1/20191225170656941.png","content":null,"comments":null,"excerpt":null,"keywords":null,"categories":[{"name":"HardwareServer","path":"api/categories/HardwareServer.json"}],"tags":[{"name":"DellServer","path":"api/tags/DellServer.json"}]}]}