{"name":"HuaweiServer","postlist":[{"title":"Huawei-2488H-V5服务器基础配置与系统安装","slug":"系统运维/Server/Huawei/Huawei-2488H-V5服务器基础配置与系统安装","date":"2020-06-26T01:34:30.000Z","updated":"2022-11-22T03:04:35.341Z","url":"2020/6-26-221.html","path":"api/articles/2020/6-26-221.html.json","cover":"https://img.weiyigeek.top/2020/1/20200711103557.png","content":null,"comments":null,"excerpt":null,"keywords":null,"categories":[{"name":"HardwareServer","path":"api/categories/HardwareServer.json"}],"tags":[{"name":"HuaweiServer","path":"api/tags/HuaweiServer.json"}]}]}